setup.cfg
setup.py
skleearn/skleearn.py
skleearn.egg-info/PKG-INFO
skleearn.egg-info/SOURCES.txt
skleearn.egg-info/dependency_links.txt
skleearn.egg-info/not-zip-safe
skleearn.egg-info/top_level.txt