Metadata-Version: 2.1
Name: skleearn
Version: 0.1
Summary: skleearn
Author-email: applepro285@gmail.com
